OASYS1-1.1.47.dist-info/DESCRIPTION.rst
OASYS1-1.1.47.dist-info/METADATA
OASYS1-1.1.47.dist-info/RECORD
OASYS1-1.1.47.dist-info/WHEEL
OASYS1-1.1.47.dist-info/entry_points.txt
OASYS1-1.1.47.dist-info/metadata.json
OASYS1-1.1.47.dist-info/top_level.txt
oasys/__init__.py
oasys/version.py
oasys/application/__init__.py
oasys/application/addons.py
oasys/canvas/__init__.py
oasys/canvas/__main__.py
oasys/canvas/conf.py
oasys/canvas/discovery.py
oasys/canvas/mainwindow.py
oasys/canvas/widgetsscheme.py
oasys/canvas/icons/Arrow.svg
oasys/canvas/icons/Back.svg
oasys/canvas/icons/Document Info.svg
oasys/canvas/icons/Documentation.svg
oasys/canvas/icons/Dropdown.svg
oasys/canvas/icons/Get Started.svg
oasys/canvas/icons/Grid.svg
oasys/canvas/icons/Info.svg
oasys/canvas/icons/Install.svg
oasys/canvas/icons/Maximize Toolbar.svg
oasys/canvas/icons/Minimize Toolbar.svg
oasys/canvas/icons/New.svg
oasys/canvas/icons/Open.svg
oasys/canvas/icons/Pause.svg
oasys/canvas/icons/Recent.svg
oasys/canvas/icons/Search.svg
oasys/canvas/icons/Text Size.svg
oasys/canvas/icons/Tutorials.svg
oasys/canvas/icons/Update.svg
oasys/canvas/icons/application.png
oasys/canvas/icons/arrow-right.svg
oasys/canvas/icons/categories.png
oasys/canvas/icons/default-category.svg
oasys/canvas/icons/default-widget.svg
oasys/canvas/icons/delete.png
oasys/canvas/icons/delete_gray.png
oasys/canvas/icons/doc.png
oasys/canvas/icons/error.png
oasys/canvas/icons/exit.png
oasys/canvas/icons/folders.png
oasys/canvas/icons/folders2.png
oasys/canvas/icons/frame.png
oasys/canvas/icons/frame2.png
oasys/canvas/icons/information.png
oasys/canvas/icons/leftEdge.png
oasys/canvas/icons/leftEdgeG.png
oasys/canvas/icons/leftEdgeR.png
oasys/canvas/icons/moveleft.png
oasys/canvas/icons/moveright.png
oasys/canvas/icons/oasys-splash-screen.png
oasys/canvas/icons/oasys.png
oasys/canvas/icons/open.png
oasys/canvas/icons/options.png
oasys/canvas/icons/orange-canvas.svg
oasys/canvas/icons/output.png
oasys/canvas/icons/print.png
oasys/canvas/icons/rightEdge.png
oasys/canvas/icons/rightEdgeG.png
oasys/canvas/icons/rightEdgeR.png
oasys/canvas/icons/save.png
oasys/canvas/icons/splash.png
oasys/canvas/icons/text.png
